meditor/__init__.py
meditor/app.py
meditor/editor.py
meditor/findreplace.py
meditor/gaction.py
meditor/globalvars.py
meditor/output.py
meditor/qrc_icon_theme.py
meditor/tab_editor.py
meditor/util.py
meditor/vim.py
meditor/webview.py
meditor/workspace.py
meditor/data/meditor-text-editor.ico
meditor/data/rst.properties
meditor/data/help/asciimath.md
meditor/data/help/basics.md
meditor/data/help/cheatsheet.md
meditor/data/help/cheatsheet.rst
meditor/data/help/demo.md
meditor/data/help/demo.rst
meditor/data/help/latex-math.md
meditor/data/help/latex-math.rst
meditor/data/help/quickstart.rst
meditor/data/help/syntax.md
meditor/data/help/images/biohazard.png
meditor/data/help/images/title.png
meditor/data/help/ref/definitions.rst
meditor/data/help/ref/directives.rst
meditor/data/help/ref/introduction.rst
meditor/data/help/ref/restructuredtext.rst
meditor/data/help/ref/roles.rst
meditor/data/math/MathJax.min.js
meditor/data/template/skeleton.html
meditor/data/template/skeleton.md
meditor/data/template/skeleton.py
meditor/data/template/skeleton.rst
meditor/data/themes/Markdown/hzlzh-markdown-theme/GitHub-ReadMe.css
meditor/data/themes/Markdown/vscode-markdown-css/markdown-dark-material.css
meditor/data/themes/Markdown/vscode-markdown-css/markdown-github.css
meditor/data/themes/Markdown/vscode-markdown-css/markdown-light.css
meditor/data/themes/Markdown/vscode-markdown-css/markdown-pdf.css
meditor/data/themes/Markdown/wecatch-markdown-css/apollo.css
meditor/data/themes/Markdown/wecatch-markdown-css/erye.css
meditor/data/themes/Markdown/wecatch-markdown-css/infoq.css
meditor/data/themes/Markdown/wecatch-markdown-css/less.css
meditor/data/themes/Markdown/wecatch-markdown-css/list-writing.css
meditor/data/themes/Markdown/wecatch-markdown-css/ocean.css
meditor/data/themes/Markdown/wecatch-markdown-css/simple.css
meditor/data/themes/Markdown/wecatch-markdown-css/style.css
meditor-2.13.38.dist-info/METADATA
meditor-2.13.38.dist-info/RECORD
meditor-2.13.38.dist-info/WHEEL
meditor-2.13.38.dist-info/entry_points.txt
meditor-2.13.38.dist-info/top_level.txt
