Metadata-Version: 2.1
Name: meditor
Version: 2.13.38
Summary: Editor for reStructuredText and Markdown
Home-page: https://github.com/liuyug/meditor.git
Author: Yugang LIU
Author-email: liuyug@gmail.com
License: UNKNOWN
Keywords: reStructuredText Markdown editor preview
Platform: noarch
Classifier: Programming Language :: Python :: 3
Classifier: License :: OSI Approved :: MIT License
Classifier: Operating System :: OS Independent
Classifier: Topic :: Text Editors :: Text Processing
Classifier: Topic :: Text Processing :: Markup
Requires-Python: >=3
Requires-Dist: PyQt5
Requires-Dist: QScintilla
Requires-Dist: Pygments
Requires-Dist: chardet
Requires-Dist: docutils
Requires-Dist: Markdown
Requires-Dist: python-markdown-mathjax
Requires-Dist: mtable
